microyc/__init__.py
microyc/auth.py
microyc/exceptions.py
microyc/inside_vm.py
microyc/objects.py
microyc/utils.py
microyc-0.1.2.dist-info/LICENSE
microyc-0.1.2.dist-info/METADATA
microyc-0.1.2.dist-info/WHEEL
microyc-0.1.2.dist-info/top_level.txt
microyc-0.1.2.dist-info/RECORD
