Metadata-Version: 2.1
Name: microyc
Version: 0.1.2
Summary: yandex.cloud minimalistic sdk
Home-page: https://github.com/thefrol/microyc
Author: Frolenko Dima
Author-email: orangefrol@gmail.com
Project-URL: GitHub, https://github.com/thefrol/microyc
Keywords: yandex,yandex.cloud
Classifier: Development Status :: 3 - Alpha
Classifier: Intended Audience :: Developers
Classifier: Topic :: Software Development :: Build Tools
Classifier: License :: OSI Approved :: MIT License
Classifier: Programming Language :: Python :: 3.8
Classifier: Programming Language :: Python :: 3.9
Classifier: Programming Language :: Python :: 3.10
Classifier: Programming Language :: Python :: 3 :: Only
Requires-Python: >=3.8, <4
License-File: LICENSE
Requires-Dist: boto3
Requires-Dist: requests
Requires-Dist: botocore
